README.md
setup.cfg
setup.py
unittest_xml_reporting_iron.egg-info/PKG-INFO
unittest_xml_reporting_iron.egg-info/SOURCES.txt
unittest_xml_reporting_iron.egg-info/dependency_links.txt
unittest_xml_reporting_iron.egg-info/not-zip-safe
unittest_xml_reporting_iron.egg-info/requires.txt
unittest_xml_reporting_iron.egg-info/top_level.txt
xmlrunner/__init__.py
xmlrunner/__main__.py
xmlrunner/builder.py
xmlrunner/result.py
xmlrunner/runner.py
xmlrunner/unittest.py
xmlrunner/version.py
xmlrunner/extra/__init__.py
xmlrunner/extra/djangotestrunner.py