Metadata-Version: 1.1
Name: unittest-xml-reporting-iron
Version: 2.2.0
Summary: unittest-based test runner with Ant/JUnit like XML reporting.
Home-page: https://github.com/rasjani/unittest-xml-reporting/tree/fix-182
Author: Jani Mikkonen
Author-email: jani.mikkonen@gmail.com
License: BSD
Keywords: pyunit,unittest,junit xml,report,testrunner,xmlrunner
Platform: Any
Classifier: Development Status :: 5 - Production/Stable
Classifier: Intended Audience :: Developers
Classifier: License :: OSI Approved :: BSD License
Classifier: Natural Language :: English
Classifier: Operating System :: OS Independent
Classifier: Programming Language :: Python
Classifier: Programming Language :: Python :: 2
Classifier: Programming Language :: Python :: 2.7
Classifier: Programming Language :: Python :: 3
Classifier: Programming Language :: Python :: 3.3
Classifier: Programming Language :: Python :: 3.4
Classifier: Programming Language :: Python :: 3.5
Classifier: Programming Language :: Python :: 3.6
Classifier: Programming Language :: Python :: Implementation :: CPython
Classifier: Programming Language :: Python :: Implementation :: PyPy
Classifier: Topic :: Software Development :: Libraries :: Python Modules
Classifier: Topic :: Software Development :: Testing
